auction_manager_x23420855/AuctionManager.py
auction_manager_x23420855/__init__.py
auction_manager_x23420855-0.0.3.dist-info/METADATA
auction_manager_x23420855-0.0.3.dist-info/WHEEL
auction_manager_x23420855-0.0.3.dist-info/licenses/LICENSE
auction_manager_x23420855-0.0.3.dist-info/RECORD
